setup.py
pyplug/__init__.py
pyplug.egg-info/PKG-INFO
pyplug.egg-info/SOURCES.txt
pyplug.egg-info/dependency_links.txt
pyplug.egg-info/requires.txt
pyplug.egg-info/top_level.txt