Metadata-Version: 1.1
Name: pyplug
Version: 0.1.2
Summary: Python plugin framework
Home-page: https://github.com/stanislavfeldman/pyplug
Author: Stanislav Feldman
Author-email: UNKNOWN
License: UNKNOWN
Keywords: plugin
Platform: UNKNOWN
Classifier: Topic :: Software Development
